infodesreg/__init__.py
infodesreg/des.py
infodesreg-0.0.9.dist-info/LICENSE
infodesreg-0.0.9.dist-info/METADATA
infodesreg-0.0.9.dist-info/WHEEL
infodesreg-0.0.9.dist-info/top_level.txt
infodesreg-0.0.9.dist-info/RECORD
