Metadata-Version: 2.1
Name: infodesreg
Version: 0.0.9
Summary: InfoDESReg: Dynamic Ensemble Selection for Regression tasks
Author-email: Panda <author@example.com>
Project-URL: Homepage, https://github.com/pypa/sampleproject
Project-URL: Issues, https://github.com/pypa/sampleproject/issues
Classifier: Programming Language :: Python :: 3
Classifier: License :: OSI Approved :: MIT License
Classifier: Operating System :: OS Independent
Requires-Python: >=3.7
License-File: LICENSE
